{
  "HomePro": {
    "LUZINO": ["CARINI", "LE", "MODERN", "EVE", "PHILIPS"],
    "GIANT KINGKONG": ["MATALL", "LE", "ACCO", "HACHI", "KING"],
    "KASSA": ["PLIM", "ACCO", "LE", "JCJ", "CLOSE"],
    "FONTE": ["SPRING", "ARAI", "SAKURA"],
    "BF": ["MATALL"]
  },
  "DoHome": {
    "LUZINO": ["LE", "LAMPTAN"],
    "GIANT KINGKONG": ["NASH", "MODERN", "LE"],
    "KASSA": ["JCJ", "LE", "MODERN", "API", "KING"],
    "ZAGIO": ["KING"]
  },
  "GlobalHouse": {
    "LUZINO": ["LE"],
    "GIANT KINGKONG": ["LE"],
    "KASSA": ["JCJ", "LE", "API", "HACHI", "CLOSE"],
    "ZAGIO": ["CLOSE"]
  },
  "Boonthavorn": {
    "LUZINO": ["MAX LIGHT", "LE"],
    "ZAGIO": ["KING"],
    "GIANT KINGKONG": ["BF", "SOMIC", "INDY", "HACHI"],
    "FONTE": ["HOMEMART", "ANYHOME", "SAKURA"]
  }
}
